setup.py
repaug/__init__.py
repaug/color_jitter.py
repaug/crop.py
repaug/flip.py
repaug/gaussian_blur.py
repaug/pepper_salt.py
repaug/rotate.py
repaug/utils.py
RepAug-0.0.1.dist-info/LICENSE
RepAug-0.0.1.dist-info/METADATA
RepAug-0.0.1.dist-info/WHEEL
RepAug-0.0.1.dist-info/top_level.txt
RepAug-0.0.1.dist-info/RECORD
