Metadata-Version: 2.1
Name: RepAug
Version: 0.0.1
Summary: A package for reproducible vision data augmentation in PyTorch.
Author-email: Yiming Ma <yiming.ma.cv@outlook.com>
Project-URL: Homepage, https://github.com/Yiming-M/RepAug
Project-URL: Bug Tracker, https://github.com/Yiming-M/RepAug/issues
Classifier: Programming Language :: Python :: 3
Classifier: License :: OSI Approved :: MIT License
Classifier: Operating System :: OS Independent
Requires-Python: >=3.7
License-File: LICENSE
